moshi_mlx/__init__.py
moshi_mlx/client_utils.py
moshi_mlx/local.py
moshi_mlx/local_web.py
moshi_mlx/py.typed
moshi_mlx/run_helium.py
moshi_mlx/run_inference.py
moshi_mlx/run_tts.py
moshi_mlx/models/__init__.py
moshi_mlx/models/generate.py
moshi_mlx/models/lm.py
moshi_mlx/models/mimi.py
moshi_mlx/models/tts.py
moshi_mlx/modules/__init__.py
moshi_mlx/modules/conditioner.py
moshi_mlx/modules/conv.py
moshi_mlx/modules/kv_cache.py
moshi_mlx/modules/quantization.py
moshi_mlx/modules/seanet.py
moshi_mlx/modules/transformer.py
moshi_mlx/utils/__init__.py
moshi_mlx/utils/loaders.py
moshi_mlx/utils/sampling.py
moshi_mlx-0.2.11.dist-info/licenses/LICENSE
moshi_mlx-0.2.11.dist-info/METADATA
moshi_mlx-0.2.11.dist-info/WHEEL
moshi_mlx-0.2.11.dist-info/entry_points.txt
moshi_mlx-0.2.11.dist-info/top_level.txt
moshi_mlx-0.2.11.dist-info/RECORD
