Metadata-Version: 2.4
Name: moshi_mlx
Version: 0.2.11
Summary: Moshi is moshi, but running on macOS
Author-email: Laurent Mazaré <laurent@kyutai.org>
Maintainer-email: Laurent Mazaré <laurent@kyutai.org>
License: MIT
Requires-Python: >=3.10
License-File: LICENSE
Requires-Dist: numpy<2.3,>=2.1.0
Requires-Dist: safetensors<0.6,>=0.4.0
Requires-Dist: huggingface-hub<0.29,>=0.24
Requires-Dist: rustymimi==0.4.1
Requires-Dist: sentencepiece==0.2
Requires-Dist: sounddevice==0.5
Requires-Dist: sphn<0.3.0,>=0.2.0
Requires-Dist: mlx<0.27,>=0.26.0
Requires-Dist: aiohttp<3.12,>=3.10.5
Provides-Extra: dev
Requires-Dist: pyright; extra == "dev"
Requires-Dist: flake8; extra == "dev"
Requires-Dist: pre-commit; extra == "dev"
Dynamic: license-file
